gym_wordle/__init__.py
gym_wordle/wordle.py
gym_wordle/envs/__init__.py
gym_wordle/envs/state.py
gym_wordle/envs/wordle-allowed-guesses.txt
gym_wordle/envs/wordle-answers-alphabetical.txt
gym_wordle/envs/wordle_env.py
gym_wordle/envs/wordle_env_easy.py
alt_gym_wordle-0.8.6.dist-info/METADATA
alt_gym_wordle-0.8.6.dist-info/WHEEL
alt_gym_wordle-0.8.6.dist-info/top_level.txt
alt_gym_wordle-0.8.6.dist-info/RECORD
