Metadata-Version: 2.1
Name: alt-gym-wordle
Version: 0.8.6
Summary: OpenAI gym environment for training agents on Wordle
Home-page: https://github.com/ryan-snyder/gym-wordle
Author: Ryan Snyder
License: UNKNOWN
Platform: UNKNOWN
Requires-Dist: gym
Requires-Dist: pandas
Requires-Dist: pygame
